{"nodes": [{"id": "frontend_src_pages_searchpage_jsx", "label": "SearchPage.jsx", "file_type": "code", "source_file": "frontend\\src\\pages\\SearchPage.jsx", "source_location": "L1"}, {"id": "searchpage_searchpage", "label": "SearchPage()", "file_type": "code", "source_file": "frontend\\src\\pages\\SearchPage.jsx", "source_location": "L13"}], "edges": [{"source": "frontend_src_pages_searchpage_jsx", "target": "react", "relation": "imports_from", "confidence": "EXTRACTED", "source_file": "frontend\\src\\pages\\SearchPage.jsx", "source_location": "L1", "weight": 1.0}, {"source": "frontend_src_pages_searchpage_jsx", "target": "react_router_dom", "relation": "imports_from", "confidence": "EXTRACTED", "source_file": "frontend\\src\\pages\\SearchPage.jsx", "source_location": "L2", "weight": 1.0}, {"source": "frontend_src_pages_searchpage_jsx", "target": "frontend_src_components_search_searchbar", "relation": "imports_from", "confidence": "EXTRACTED", "source_file": "frontend\\src\\pages\\SearchPage.jsx", "source_location": "L3", "weight": 1.0}, {"source": "frontend_src_pages_searchpage_jsx", "target": "frontend_src_components_search_filtersidebar", "relation": "imports_from", "confidence": "EXTRACTED", "source_file": "frontend\\src\\pages\\SearchPage.jsx", "source_location": "L4", "weight": 1.0}, {"source": "frontend_src_pages_searchpage_jsx", "target": "frontend_src_components_search_activefilterchips", "relation": "imports_from", "confidence": "EXTRACTED", "source_file": "frontend\\src\\pages\\SearchPage.jsx", "source_location": "L5", "weight": 1.0}, {"source": "frontend_src_pages_searchpage_jsx", "target": "frontend_src_components_search_conversationalpanel", "relation": "imports_from", "confidence": "EXTRACTED", "source_file": "frontend\\src\\pages\\SearchPage.jsx", "source_location": "L6", "weight": 1.0}, {"source": "frontend_src_pages_searchpage_jsx", "target": "frontend_src_components_search_resultslist", "relation": "imports_from", "confidence": "EXTRACTED", "source_file": "frontend\\src\\pages\\SearchPage.jsx", "source_location": "L7", "weight": 1.0}, {"source": "frontend_src_pages_searchpage_jsx", "target": "frontend_src_components_search_pagination", "relation": "imports_from", "confidence": "EXTRACTED", "source_file": "frontend\\src\\pages\\SearchPage.jsx", "source_location": "L8", "weight": 1.0}, {"source": "frontend_src_pages_searchpage_jsx", "target": "frontend_src_components_shared_scorebreakdown", "relation": "imports_from", "confidence": "EXTRACTED", "source_file": "frontend\\src\\pages\\SearchPage.jsx", "source_location": "L9", "weight": 1.0}, {"source": "frontend_src_pages_searchpage_jsx", "target": "frontend_src_hooks_usesearch", "relation": "imports_from", "confidence": "EXTRACTED", "source_file": "frontend\\src\\pages\\SearchPage.jsx", "source_location": "L10", "weight": 1.0}, {"source": "frontend_src_pages_searchpage_jsx", "target": "frontend_src_hooks_usefilters", "relation": "imports_from", "confidence": "EXTRACTED", "source_file": "frontend\\src\\pages\\SearchPage.jsx", "source_location": "L11", "weight": 1.0}, {"source": "frontend_src_pages_searchpage_jsx", "target": "searchpage_searchpage", "relation": "contains", "confidence": "EXTRACTED", "source_file": "frontend\\src\\pages\\SearchPage.jsx", "source_location": "L13", "weight": 1.0}], "raw_calls": [{"caller_nid": "searchpage_searchpage", "callee": "useSearchParams", "source_file": "frontend\\src\\pages\\SearchPage.jsx", "source_location": "L14"}, {"caller_nid": "searchpage_searchpage", "callee": "useNavigate", "source_file": "frontend\\src\\pages\\SearchPage.jsx", "source_location": "L15"}, {"caller_nid": "searchpage_searchpage", "callee": "get", "source_file": "frontend\\src\\pages\\SearchPage.jsx", "source_location": "L16"}, {"caller_nid": "searchpage_searchpage", "callee": "useFilters", "source_file": "frontend\\src\\pages\\SearchPage.jsx", "source_location": "L27"}, {"caller_nid": "searchpage_searchpage", "callee": "useSearch", "source_file": "frontend\\src\\pages\\SearchPage.jsx", "source_location": "L45"}, {"caller_nid": "searchpage_searchpage", "callee": "useState", "source_file": "frontend\\src\\pages\\SearchPage.jsx", "source_location": "L47"}, {"caller_nid": "searchpage_searchpage", "callee": "useRef", "source_file": "frontend\\src\\pages\\SearchPage.jsx", "source_location": "L48"}, {"caller_nid": "searchpage_searchpage", "callee": "useEffect", "source_file": "frontend\\src\\pages\\SearchPage.jsx", "source_location": "L51"}, {"caller_nid": "searchpage_searchpage", "callee": "useEffect", "source_file": "frontend\\src\\pages\\SearchPage.jsx", "source_location": "L58"}]}